{
  "formatVersion": 1,
  "database": {
    "version": 3,
    "identityHash": "d72f845442bc8a1bb54b397db48edd27",
    "entities": [
      {
        "tableName": "county",
        "createSql": "CREATE TABLE IF NOT EXISTS `${TABLE_NAME}` (`id` INTEGER PRIMARY KEY AUTOINCREMENT NOT NULL, `name` TEXT NOT NULL, `pref_order` INTEGER NOT NULL)",
        "fields": [
          {
            "fieldPath": "id",
            "columnName": "id",
            "affinity": "INTEGER",
            "notNull": true
          },
          {
            "fieldPath": "name",
            "columnName": "name",
            "affinity": "TEXT",
            "notNull": true
          },
          {
            "fieldPath": "prefOrder",
            "columnName": "pref_order",
            "affinity": "INTEGER",
            "notNull": true
          }
        ],
        "primaryKey": {
          "autoGenerate": true,
          "columnNames": [
            "id"
          ]
        },
        "indices": [
          {
            "name": "index_county_name",
            "unique": true,
            "columnNames": [
              "name"
            ],
            "orders": [],
            "createSql": "CREATE UNIQUE INDEX IF NOT EXISTS `index_county_name` ON `${TABLE_NAME}` (`name`)"
          }
        ],
        "foreignKeys": []
      },
      {
        "tableName": "wine",
        "createSql": "CREATE TABLE IF NOT EXISTS `${TABLE_NAME}` (`id` INTEGER PRIMARY KEY AUTOINCREMENT NOT NULL, `name` TEXT NOT NULL, `naming` TEXT NOT NULL, `color` TEXT NOT NULL, `cuvee` TEXT NOT NULL, `is_organic` INTEGER NOT NULL, `img_path` TEXT NOT NULL, `county_id` INTEGER NOT NULL, `hidden` INTEGER NOT NULL, FOREIGN KEY(`county_id`) REFERENCES `county`(`id`) ON UPDATE NO ACTION ON DELETE CASCADE )",
        "fields": [
          {
            "fieldPath": "id",
            "columnName": "id",
            "affinity": "INTEGER",
            "notNull": true
          },
          {
            "fieldPath": "name",
            "columnName": "name",
            "affinity": "TEXT",
            "notNull": true
          },
          {
            "fieldPath": "naming",
            "columnName": "naming",
            "affinity": "TEXT",
            "notNull": true
          },
          {
            "fieldPath": "color",
            "columnName": "color",
            "affinity": "TEXT",
            "notNull": true
          },
          {
            "fieldPath": "cuvee",
            "columnName": "cuvee",
            "affinity": "TEXT",
            "notNull": true
          },
          {
            "fieldPath": "isOrganic",
            "columnName": "is_organic",
            "affinity": "INTEGER",
            "notNull": true
          },
          {
            "fieldPath": "imgPath",
            "columnName": "img_path",
            "affinity": "TEXT",
            "notNull": true
          },
          {
            "fieldPath": "countyId",
            "columnName": "county_id",
            "affinity": "INTEGER",
            "notNull": true
          },
          {
            "fieldPath": "hidden",
            "columnName": "hidden",
            "affinity": "INTEGER",
            "notNull": true
          }
        ],
        "primaryKey": {
          "autoGenerate": true,
          "columnNames": [
            "id"
          ]
        },
        "indices": [
          {
            "name": "index_wine_county_id",
            "unique": false,
            "columnNames": [
              "county_id"
            ],
            "orders": [],
            "createSql": "CREATE INDEX IF NOT EXISTS `index_wine_county_id` ON `${TABLE_NAME}` (`county_id`)"
          }
        ],
        "foreignKeys": [
          {
            "table": "county",
            "onDelete": "CASCADE",
            "onUpdate": "NO ACTION",
            "columns": [
              "county_id"
            ],
            "referencedColumns": [
              "id"
            ]
          }
        ]
      },
      {
        "tableName": "bottle",
        "createSql": "CREATE TABLE IF NOT EXISTS `${TABLE_NAME}` (`id` INTEGER PRIMARY KEY AUTOINCREMENT NOT NULL, `wine_id` INTEGER NOT NULL, `vintage` INTEGER NOT NULL, `apogee` INTEGER, `is_favorite` INTEGER NOT NULL, `price` REAL NOT NULL, `currency` TEXT NOT NULL, `other_info` TEXT NOT NULL, `buy_location` TEXT NOT NULL, `buy_date` INTEGER NOT NULL, `tasting_taste_comment` TEXT NOT NULL, `bottle_size` TEXT NOT NULL, `pdf_path` TEXT NOT NULL, `storage_location` TEXT NOT NULL DEFAULT '', `alcohol` REAL, `consumed` INTEGER NOT NULL, `tasting_id` INTEGER, FOREIGN KEY(`wine_id`) REFERENCES `wine`(`id`) ON UPDATE NO ACTION ON DELETE CASCADE )",
        "fields": [
          {
            "fieldPath": "id",
            "columnName": "id",
            "affinity": "INTEGER",
            "notNull": true
          },
          {
            "fieldPath": "wineId",
            "columnName": "wine_id",
            "affinity": "INTEGER",
            "notNull": true
          },
          {
            "fieldPath": "vintage",
            "columnName": "vintage",
            "affinity": "INTEGER",
            "notNull": true
          },
          {
            "fieldPath": "apogee",
            "columnName": "apogee",
            "affinity": "INTEGER",
            "notNull": false
          },
          {
            "fieldPath": "isFavorite",
            "columnName": "is_favorite",
            "affinity": "INTEGER",
            "notNull": true
          },
          {
            "fieldPath": "price",
            "columnName": "price",
            "affinity": "REAL",
            "notNull": true
          },
          {
            "fieldPath": "currency",
            "columnName": "currency",
            "affinity": "TEXT",
            "notNull": true
          },
          {
            "fieldPath": "otherInfo",
            "columnName": "other_info",
            "affinity": "TEXT",
            "notNull": true
          },
          {
            "fieldPath": "buyLocation",
            "columnName": "buy_location",
            "affinity": "TEXT",
            "notNull": true
          },
          {
            "fieldPath": "buyDate",
            "columnName": "buy_date",
            "affinity": "INTEGER",
            "notNull": true
          },
          {
            "fieldPath": "tastingTasteComment",
            "columnName": "tasting_taste_comment",
            "affinity": "TEXT",
            "notNull": true
          },
          {
            "fieldPath": "bottleSize",
            "columnName": "bottle_size",
            "affinity": "TEXT",
            "notNull": true
          },
          {
            "fieldPath": "pdfPath",
            "columnName": "pdf_path",
            "affinity": "TEXT",
            "notNull": true
          },
          {
            "fieldPath": "storageLocation",
            "columnName": "storage_location",
            "affinity": "TEXT",
            "notNull": true,
            "defaultValue": "''"
          },
          {
            "fieldPath": "alcohol",
            "columnName": "alcohol",
            "affinity": "REAL",
            "notNull": false
          },
          {
            "fieldPath": "consumed",
            "columnName": "consumed",
            "affinity": "INTEGER",
            "notNull": true
          },
          {
            "fieldPath": "tastingId",
            "columnName": "tasting_id",
            "affinity": "INTEGER",
            "notNull": false
          }
        ],
        "primaryKey": {
          "autoGenerate": true,
          "columnNames": [
            "id"
          ]
        },
        "indices": [
          {
            "name": "index_bottle_wine_id",
            "unique": false,
            "columnNames": [
              "wine_id"
            ],
            "orders": [],
            "createSql": "CREATE INDEX IF NOT EXISTS `index_bottle_wine_id` ON `${TABLE_NAME}` (`wine_id`)"
          },
          {
            "name": "index_bottle_tasting_id",
            "unique": false,
            "columnNames": [
              "tasting_id"
            ],
            "orders": [],
            "createSql": "CREATE INDEX IF NOT EXISTS `index_bottle_tasting_id` ON `${TABLE_NAME}` (`tasting_id`)"
          }
        ],
        "foreignKeys": [
          {
            "table": "wine",
            "onDelete": "CASCADE",
            "onUpdate": "NO ACTION",
            "columns": [
              "wine_id"
            ],
            "referencedColumns": [
              "id"
            ]
          }
        ]
      },
      {
        "tableName": "grape",
        "createSql": "CREATE TABLE IF NOT EXISTS `${TABLE_NAME}` (`id` INTEGER PRIMARY KEY AUTOINCREMENT NOT NULL, `name` TEXT NOT NULL)",
        "fields": [
          {
            "fieldPath": "id",
            "columnName": "id",
            "affinity": "INTEGER",
            "notNull": true
          },
          {
            "fieldPath": "name",
            "columnName": "name",
            "affinity": "TEXT",
            "notNull": true
          }
        ],
        "primaryKey": {
          "autoGenerate": true,
          "columnNames": [
            "id"
          ]
        },
        "indices": [
          {
            "name": "index_grape_name",
            "unique": true,
            "columnNames": [
              "name"
            ],
            "orders": [],
            "createSql": "CREATE UNIQUE INDEX IF NOT EXISTS `index_grape_name` ON `${TABLE_NAME}` (`name`)"
          }
        ],
        "foreignKeys": []
      },
      {
        "tableName": "review",
        "createSql": "CREATE TABLE IF NOT EXISTS `${TABLE_NAME}` (`id` INTEGER PRIMARY KEY AUTOINCREMENT NOT NULL, `contest_name` TEXT NOT NULL, `type` INTEGER NOT NULL)",
        "fields": [
          {
            "fieldPath": "id",
            "columnName": "id",
            "affinity": "INTEGER",
            "notNull": true
          },
          {
            "fieldPath": "contestName",
            "columnName": "contest_name",
            "affinity": "TEXT",
            "notNull": true
          },
          {
            "fieldPath": "type",
            "columnName": "type",
            "affinity": "INTEGER",
            "notNull": true
          }
        ],
        "primaryKey": {
          "autoGenerate": true,
          "columnNames": [
            "id"
          ]
        },
        "indices": [
          {
            "name": "index_review_contest_name",
            "unique": true,
            "columnNames": [
              "contest_name"
            ],
            "orders": [],
            "createSql": "CREATE UNIQUE INDEX IF NOT EXISTS `index_review_contest_name` ON `${TABLE_NAME}` (`contest_name`)"
          }
        ],
        "foreignKeys": []
      },
      {
        "tableName": "q_grape",
        "createSql": "CREATE TABLE IF NOT EXISTS `${TABLE_NAME}` (`bottle_id` INTEGER NOT NULL, `grape_id` INTEGER NOT NULL, `percentage` INTEGER NOT NULL, PRIMARY KEY(`bottle_id`, `grape_id`), FOREIGN KEY(`bottle_id`) REFERENCES `bottle`(`id`) ON UPDATE NO ACTION ON DELETE CASCADE , FOREIGN KEY(`grape_id`) REFERENCES `grape`(`id`) ON UPDATE NO ACTION ON DELETE CASCADE )",
        "fields": [
          {
            "fieldPath": "bottleId",
            "columnName": "bottle_id",
            "affinity": "INTEGER",
            "notNull": true
          },
          {
            "fieldPath": "grapeId",
            "columnName": "grape_id",
            "affinity": "INTEGER",
            "notNull": true
          },
          {
            "fieldPath": "percentage",
            "columnName": "percentage",
            "affinity": "INTEGER",
            "notNull": true
          }
        ],
        "primaryKey": {
          "autoGenerate": false,
          "columnNames": [
            "bottle_id",
            "grape_id"
          ]
        },
        "indices": [
          {
            "name": "index_q_grape_grape_id",
            "unique": false,
            "columnNames": [
              "grape_id"
            ],
            "orders": [],
            "createSql": "CREATE INDEX IF NOT EXISTS `index_q_grape_grape_id` ON `${TABLE_NAME}` (`grape_id`)"
          }
        ],
        "foreignKeys": [
          {
            "table": "bottle",
            "onDelete": "CASCADE",
            "onUpdate": "NO ACTION",
            "columns": [
              "bottle_id"
            ],
            "referencedColumns": [
              "id"
            ]
          },
          {
            "table": "grape",
            "onDelete": "CASCADE",
            "onUpdate": "NO ACTION",
            "columns": [
              "grape_id"
            ],
            "referencedColumns": [
              "id"
            ]
          }
        ]
      },
      {
        "tableName": "f_review",
        "createSql": "CREATE TABLE IF NOT EXISTS `${TABLE_NAME}` (`bottle_id` INTEGER NOT NULL, `review_id` INTEGER NOT NULL, `value` INTEGER NOT NULL, PRIMARY KEY(`bottle_id`, `review_id`), FOREIGN KEY(`bottle_id`) REFERENCES `bottle`(`id`) ON UPDATE NO ACTION ON DELETE CASCADE , FOREIGN KEY(`review_id`) REFERENCES `review`(`id`) ON UPDATE NO ACTION ON DELETE CASCADE )",
        "fields": [
          {
            "fieldPath": "bottleId",
            "columnName": "bottle_id",
            "affinity": "INTEGER",
            "notNull": true
          },
          {
            "fieldPath": "reviewId",
            "columnName": "review_id",
            "affinity": "INTEGER",
            "notNull": true
          },
          {
            "fieldPath": "value",
            "columnName": "value",
            "affinity": "INTEGER",
            "notNull": true
          }
        ],
        "primaryKey": {
          "autoGenerate": false,
          "columnNames": [
            "bottle_id",
            "review_id"
          ]
        },
        "indices": [
          {
            "name": "index_f_review_review_id",
            "unique": false,
            "columnNames": [
              "review_id"
            ],
            "orders": [],
            "createSql": "CREATE INDEX IF NOT EXISTS `index_f_review_review_id` ON `${TABLE_NAME}` (`review_id`)"
          }
        ],
        "foreignKeys": [
          {
            "table": "bottle",
            "onDelete": "CASCADE",
            "onUpdate": "NO ACTION",
            "columns": [
              "bottle_id"
            ],
            "referencedColumns": [
              "id"
            ]
          },
          {
            "table": "review",
            "onDelete": "CASCADE",
            "onUpdate": "NO ACTION",
            "columns": [
              "review_id"
            ],
            "referencedColumns": [
              "id"
            ]
          }
        ]
      },
      {
        "tableName": "history_entry",
        "createSql": "CREATE TABLE IF NOT EXISTS `${TABLE_NAME}` (`id` INTEGER PRIMARY KEY AUTOINCREMENT NOT NULL, `date` INTEGER NOT NULL, `bottle_id` INTEGER NOT NULL, `tasting_id` INTEGER, `comment` TEXT NOT NULL, `type` INTEGER NOT NULL, `favorite` INTEGER NOT NULL, FOREIGN KEY(`bottle_id`) REFERENCES `bottle`(`id`) ON UPDATE NO ACTION ON DELETE CASCADE )",
        "fields": [
          {
            "fieldPath": "id",
            "columnName": "id",
            "affinity": "INTEGER",
            "notNull": true
          },
          {
            "fieldPath": "date",
            "columnName": "date",
            "affinity": "INTEGER",
            "notNull": true
          },
          {
            "fieldPath": "bottleId",
            "columnName": "bottle_id",
            "affinity": "INTEGER",
            "notNull": true
          },
          {
            "fieldPath": "tastingId",
            "columnName": "tasting_id",
            "affinity": "INTEGER",
            "notNull": false
          },
          {
            "fieldPath": "comment",
            "columnName": "comment",
            "affinity": "TEXT",
            "notNull": true
          },
          {
            "fieldPath": "type",
            "columnName": "type",
            "affinity": "INTEGER",
            "notNull": true
          },
          {
            "fieldPath": "favorite",
            "columnName": "favorite",
            "affinity": "INTEGER",
            "notNull": true
          }
        ],
        "primaryKey": {
          "autoGenerate": true,
          "columnNames": [
            "id"
          ]
        },
        "indices": [
          {
            "name": "index_history_entry_bottle_id",
            "unique": false,
            "columnNames": [
              "bottle_id"
            ],
            "orders": [],
            "createSql": "CREATE INDEX IF NOT EXISTS `index_history_entry_bottle_id` ON `${TABLE_NAME}` (`bottle_id`)"
          }
        ],
        "foreignKeys": [
          {
            "table": "bottle",
            "onDelete": "CASCADE",
            "onUpdate": "NO ACTION",
            "columns": [
              "bottle_id"
            ],
            "referencedColumns": [
              "id"
            ]
          }
        ]
      },
      {
        "tableName": "friend",
        "createSql": "CREATE TABLE IF NOT EXISTS `${TABLE_NAME}` (`id` INTEGER PRIMARY KEY AUTOINCREMENT NOT NULL, `name` TEXT NOT NULL, `img_path` TEXT NOT NULL)",
        "fields": [
          {
            "fieldPath": "id",
            "columnName": "id",
            "affinity": "INTEGER",
            "notNull": true
          },
          {
            "fieldPath": "name",
            "columnName": "name",
            "affinity": "TEXT",
            "notNull": true
          },
          {
            "fieldPath": "imgPath",
            "columnName": "img_path",
            "affinity": "TEXT",
            "notNull": true
          }
        ],
        "primaryKey": {
          "autoGenerate": true,
          "columnNames": [
            "id"
          ]
        },
        "indices": [
          {
            "name": "index_friend_name",
            "unique": true,
            "columnNames": [
              "name"
            ],
            "orders": [],
            "createSql": "CREATE UNIQUE INDEX IF NOT EXISTS `index_friend_name` ON `${TABLE_NAME}` (`name`)"
          }
        ],
        "foreignKeys": []
      },
      {
        "tableName": "tasting",
        "createSql": "CREATE TABLE IF NOT EXISTS `${TABLE_NAME}` (`id` INTEGER PRIMARY KEY AUTOINCREMENT NOT NULL, `date` INTEGER NOT NULL, `isMidday` INTEGER NOT NULL, `opportunity` TEXT NOT NULL, `done` INTEGER NOT NULL)",
        "fields": [
          {
            "fieldPath": "id",
            "columnName": "id",
            "affinity": "INTEGER",
            "notNull": true
          },
          {
            "fieldPath": "date",
            "columnName": "date",
            "affinity": "INTEGER",
            "notNull": true
          },
          {
            "fieldPath": "isMidday",
            "columnName": "isMidday",
            "affinity": "INTEGER",
            "notNull": true
          },
          {
            "fieldPath": "opportunity",
            "columnName": "opportunity",
            "affinity": "TEXT",
            "notNull": true
          },
          {
            "fieldPath": "done",
            "columnName": "done",
            "affinity": "INTEGER",
            "notNull": true
          }
        ],
        "primaryKey": {
          "autoGenerate": true,
          "columnNames": [
            "id"
          ]
        },
        "indices": [],
        "foreignKeys": []
      },
      {
        "tableName": "tasting_friend_xref",
        "createSql": "CREATE TABLE IF NOT EXISTS `${TABLE_NAME}` (`tasting_id` INTEGER NOT NULL, `friend_id` INTEGER NOT NULL, PRIMARY KEY(`tasting_id`, `friend_id`), FOREIGN KEY(`tasting_id`) REFERENCES `tasting`(`id`) ON UPDATE NO ACTION ON DELETE CASCADE , FOREIGN KEY(`friend_id`) REFERENCES `friend`(`id`) ON UPDATE NO ACTION ON DELETE CASCADE )",
        "fields": [
          {
            "fieldPath": "tastingId",
            "columnName": "tasting_id",
            "affinity": "INTEGER",
            "notNull": true
          },
          {
            "fieldPath": "friendId",
            "columnName": "friend_id",
            "affinity": "INTEGER",
            "notNull": true
          }
        ],
        "primaryKey": {
          "autoGenerate": false,
          "columnNames": [
            "tasting_id",
            "friend_id"
          ]
        },
        "indices": [
          {
            "name": "index_tasting_friend_xref_tasting_id",
            "unique": false,
            "columnNames": [
              "tasting_id"
            ],
            "orders": [],
            "createSql": "CREATE INDEX IF NOT EXISTS `index_tasting_friend_xref_tasting_id` ON `${TABLE_NAME}` (`tasting_id`)"
          },
          {
            "name": "index_tasting_friend_xref_friend_id",
            "unique": false,
            "columnNames": [
              "friend_id"
            ],
            "orders": [],
            "createSql": "CREATE INDEX IF NOT EXISTS `index_tasting_friend_xref_friend_id` ON `${TABLE_NAME}` (`friend_id`)"
          }
        ],
        "foreignKeys": [
          {
            "table": "tasting",
            "onDelete": "CASCADE",
            "onUpdate": "NO ACTION",
            "columns": [
              "tasting_id"
            ],
            "referencedColumns": [
              "id"
            ]
          },
          {
            "table": "friend",
            "onDelete": "CASCADE",
            "onUpdate": "NO ACTION",
            "columns": [
              "friend_id"
            ],
            "referencedColumns": [
              "id"
            ]
          }
        ]
      },
      {
        "tableName": "friend_history_entry_xref",
        "createSql": "CREATE TABLE IF NOT EXISTS `${TABLE_NAME}` (`history_entry_id` INTEGER NOT NULL, `friend_id` INTEGER NOT NULL, PRIMARY KEY(`friend_id`, `history_entry_id`), FOREIGN KEY(`friend_id`) REFERENCES `friend`(`id`) ON UPDATE NO ACTION ON DELETE CASCADE , FOREIGN KEY(`history_entry_id`) REFERENCES `history_entry`(`id`) ON UPDATE NO ACTION ON DELETE CASCADE )",
        "fields": [
          {
            "fieldPath": "historyEntryId",
            "columnName": "history_entry_id",
            "affinity": "INTEGER",
            "notNull": true
          },
          {
            "fieldPath": "friendId",
            "columnName": "friend_id",
            "affinity": "INTEGER",
            "notNull": true
          }
        ],
        "primaryKey": {
          "autoGenerate": false,
          "columnNames": [
            "friend_id",
            "history_entry_id"
          ]
        },
        "indices": [
          {
            "name": "index_friend_history_entry_xref_history_entry_id",
            "unique": false,
            "columnNames": [
              "history_entry_id"
            ],
            "orders": [],
            "createSql": "CREATE INDEX IF NOT EXISTS `index_friend_history_entry_xref_history_entry_id` ON `${TABLE_NAME}` (`history_entry_id`)"
          },
          {
            "name": "index_friend_history_entry_xref_friend_id",
            "unique": false,
            "columnNames": [
              "friend_id"
            ],
            "orders": [],
            "createSql": "CREATE INDEX IF NOT EXISTS `index_friend_history_entry_xref_friend_id` ON `${TABLE_NAME}` (`friend_id`)"
          }
        ],
        "foreignKeys": [
          {
            "table": "friend",
            "onDelete": "CASCADE",
            "onUpdate": "NO ACTION",
            "columns": [
              "friend_id"
            ],
            "referencedColumns": [
              "id"
            ]
          },
          {
            "table": "history_entry",
            "onDelete": "CASCADE",
            "onUpdate": "NO ACTION",
            "columns": [
              "history_entry_id"
            ],
            "referencedColumns": [
              "id"
            ]
          }
        ]
      },
      {
        "tableName": "tasting_action",
        "createSql": "CREATE TABLE IF NOT EXISTS `${TABLE_NAME}` (`id` INTEGER PRIMARY KEY AUTOINCREMENT NOT NULL, `type` TEXT NOT NULL, `bottle_id` INTEGER NOT NULL, `done` INTEGER NOT NULL, FOREIGN KEY(`bottle_id`) REFERENCES `bottle`(`id`) ON UPDATE NO ACTION ON DELETE CASCADE )",
        "fields": [
          {
            "fieldPath": "id",
            "columnName": "id",
            "affinity": "INTEGER",
            "notNull": true
          },
          {
            "fieldPath": "type",
            "columnName": "type",
            "affinity": "TEXT",
            "notNull": true
          },
          {
            "fieldPath": "bottleId",
            "columnName": "bottle_id",
            "affinity": "INTEGER",
            "notNull": true
          },
          {
            "fieldPath": "done",
            "columnName": "done",
            "affinity": "INTEGER",
            "notNull": true
          }
        ],
        "primaryKey": {
          "autoGenerate": true,
          "columnNames": [
            "id"
          ]
        },
        "indices": [
          {
            "name": "index_tasting_action_bottle_id",
            "unique": false,
            "columnNames": [
              "bottle_id"
            ],
            "orders": [],
            "createSql": "CREATE INDEX IF NOT EXISTS `index_tasting_action_bottle_id` ON `${TABLE_NAME}` (`bottle_id`)"
          }
        ],
        "foreignKeys": [
          {
            "table": "bottle",
            "onDelete": "CASCADE",
            "onUpdate": "NO ACTION",
            "columns": [
              "bottle_id"
            ],
            "referencedColumns": [
              "id"
            ]
          }
        ]
      }
    ],
    "views": [],
    "setupQueries": [
      "CREATE TABLE IF NOT EXISTS room_master_table (id INTEGER PRIMARY KEY,identity_hash TEXT)",
      "INSERT OR REPLACE INTO room_master_table (id,identity_hash) VALUES(42, 'd72f845442bc8a1bb54b397db48edd27')"
    ]
  }
}